dearcygui/__init__.pxd
dearcygui/__init__.py
dearcygui/c_types.pxd
dearcygui/core.pxd
dearcygui/core.pyi
dearcygui/dearcygui.cpython-313-x86_64-linux-gnu.so
dearcygui/draw.pxd
dearcygui/draw_helpers.pxd
dearcygui/font.pxd
dearcygui/handler.pxd
dearcygui/imgui.pxd
dearcygui/imgui_types.pxd
dearcygui/layout.pxd
dearcygui/lmmono10-regular.otf
dearcygui/lmromandemi10-oblique.otf
dearcygui/lmromanslant10-regular.otf
dearcygui/lmsans10-bold.otf
dearcygui/lmsans17-regular.otf
dearcygui/os.pxd
dearcygui/os.pyi
dearcygui/plot.pxd
dearcygui/py.typed
dearcygui/sizing.cpython-313-x86_64-linux-gnu.so
dearcygui/sizing.pxd
dearcygui/table.pxd
dearcygui/texture.pxd
dearcygui/theme.pxd
dearcygui/types.pxd
dearcygui/widget.pxd
dearcygui/backends/__init__.pxd
dearcygui/backends/backend.pxd
dearcygui/backends/time.pxd
dearcygui/docs/UI.md
dearcygui/docs/advanced.md
dearcygui/docs/basics.md
dearcygui/docs/callbacks.md
dearcygui/docs/drawings.md
dearcygui/docs/plots.md
dearcygui/docs/themes.md
dearcygui/utils/__init__.py
dearcygui/utils/asyncio_helpers.py
dearcygui/utils/draw.cpython-313-x86_64-linux-gnu.so
dearcygui/utils/draw.pyi
dearcygui/utils/draw_draggable.py
dearcygui/utils/handler.py
dearcygui/utils/image.cpython-313-x86_64-linux-gnu.so
dearcygui/utils/image.pyi
dearcygui/utils/layout.py
dearcygui/utils/plot.py
dearcygui/utils/widget.py
dearcygui/utils/window.py
dearcygui/wrapper/__init__.pxd
dearcygui/wrapper/delaunator.pxd
dearcygui/wrapper/freetype.pxd
dearcygui/wrapper/gc.pxd
dearcygui/wrapper/imgui.pxd
dearcygui/wrapper/implot.pxd
dearcygui.libs/libcrypt-52aca757.so.1.1.0
dearcygui-0.1.5.dist-info/METADATA
dearcygui-0.1.5.dist-info/WHEEL
dearcygui-0.1.5.dist-info/top_level.txt
dearcygui-0.1.5.dist-info/RECORD
dearcygui-0.1.5.dist-info/licenses/LICENSE
